CiscoSecurityDevice/__init__.py
CiscoSecurityDevice/exception.py
CiscoSecurityDevice/version.py
CiscoSecurityDevice/fmcDetail/__init__.py
CiscoSecurityDevice/iseDetail/__init__.py
CiscoSecurityDevice-0.0.8.dist-info/METADATA
CiscoSecurityDevice-0.0.8.dist-info/WHEEL
CiscoSecurityDevice-0.0.8.dist-info/top_level.txt
CiscoSecurityDevice-0.0.8.dist-info/RECORD
