Metadata-Version: 2.1
Name: CiscoSecurityDevice
Version: 0.0.8
Summary: This wrapper is designed to provide a unique interface to interact with ISE and FMC api.
Home-page: UNKNOWN
Author: Madhuri Dewangan
Author-email: madewang@cisco.com
License: UNKNOWN
Platform: UNKNOWN
Classifier: License :: OSI Approved :: GNU General Public License v3 (GPLv3)
Classifier: Operating System :: OS Independent
Classifier: Programming Language :: Python :: 3.7
Requires-Python: >=3.7
Requires-Dist: requests
Requires-Dist: ISE
Requires-Dist: fireREST
